[
	{
		"title": "Boolean algebra",
		"duration": "20 lessons",
		"mark": "5",
		"certificate": "./ceritificates/mshp/maths.png"
	},
	{
		"title": "Algorhitms",
		"duration": "19 lessons",
		"mark": "4+",
		"certificate": "./ceritificates/mshp/algorhitms.png"
	},
	{
		"title": "Computer Networks",
		"duration": "17 lessons",
		"mark": "5",
		"certificate": "./ceritificates/mshp/networks.png"
	},
	{
		"title": "Introduction to Python",
		"duration": "18 lessons",
		"mark": "5",
		"certificate": "./ceritificates/mshp/python.png"
	},
	{
		"title": "Olymp Python",
		"duration": "12 lessons",
		"mark": "-",
		"certificate": "./ceritificates/mshp/olymp_python.png"
	},
	{
		"title": "Data Science",
		"duration": "18 lessons",
		"mark": "5-",
		"certificate": "./ceritificates/mshp/data_science.png"
	},
	{
		"title": "Web Development",
		"duration": "17 lessons",
		"mark": "5",
		"certificate": "./ceritificates/mshp/web.png"
	},
	{
		"title": "ะก++ 1-st Year",
		"duration": "20 lessons",
		"mark": "5",
		"certificate": "./ceritificates/mshp/c++1.png"
	},
	{
		"title": "ะก++ 2-d Year",
		"duration": "19 lessons",
		"mark": "5",
		"certificate": "./ceritificates/mshp/c++2.png"
	},
	{
		"title": "AVR Assembly",
		"duration": "18 lessons",
		"mark": "5-",
		"certificate": "./ceritificates/mshp/python.png"
	},
	{
		"title": "Linux Pro",
		"duration": "17 lessons",
		"mark": "5+",
		"certificate": "./ceritificates/mshp/linux.png"
	},
	{
		"title": "Intro to CTF",
		"duration": "10 lessons",
		"mark": "-",
		"certificate": "./ceritificates/mshp/ctf.png"
	}
]